structured_report/__init__.py
structured_report/main.py
structured_report/models.py
structured_report-0.1.1.dist-info/licenses/LICENSE
structured_report-0.1.1.dist-info/METADATA
structured_report-0.1.1.dist-info/WHEEL
structured_report-0.1.1.dist-info/entry_points.txt
structured_report-0.1.1.dist-info/top_level.txt
structured_report-0.1.1.dist-info/RECORD
