Metadata-Version: 2.4
Name: structured-report
Version: 0.1.1
Summary: Transform text into structured thought models for deep learning
Author-email: Fangzhong Liu <fangzhongliu@example.com>
License: MIT
Project-URL: Homepage, https://github.com/yourusername/structured-report
Project-URL: Repository, https://github.com/yourusername/structured-report
Project-URL: Issues, https://github.com/yourusername/structured-report/issues
Project-URL: Documentation, https://github.com/yourusername/structured-report#readme
Keywords: ai,learning,thinking,analysis,fastapi
Classifier: Development Status :: 3 - Alpha
Classifier: Intended Audience :: Developers
Classifier: License :: OSI Approved :: MIT License
Classifier: Programming Language :: Python :: 3
Classifier: Programming Language :: Python :: 3.8
Classifier: Programming Language :: Python :: 3.9
Classifier: Programming Language :: Python :: 3.10
Classifier: Programming Language :: Python :: 3.11
Classifier: Topic :: Education
Classifier: Topic :: Scientific/Engineering :: Artificial Intelligence
Requires-Python: >=3.8
License-File: LICENSE
Requires-Dist: fastapi>=0.104.0
Requires-Dist: uvicorn>=0.24.0
Requires-Dist: pydantic>=2.5.0
Requires-Dist: httpx>=0.25.0
Requires-Dist: python-dotenv>=1.0.0
Requires-Dist: openai>=1.3.0
Requires-Dist: slowapi>=0.1.9
Dynamic: license-file
